Metadata-Version: 2.1
Name: promptdesigner
Version: 0.0.3
Summary: Prompt Designer is a component of Experiment Maker. It allows to create prompts to perform in-context learning with GPT-3
Home-page: https://github.com/patriziobellan86/ExperimentMaker
Author: Patrizio Bellan
Author-email: patrizio.bellan@gmail.com
License: MIT
Classifier: License :: OSI Approved :: MIT License
Classifier: Programming Language :: Python :: 3
Classifier: Programming Language :: Python :: 3.9
License-File: LICENSE
